abimca/__init__.py
abimca/autoencoders.py
abimca/losses.py
abimca/subsequence_identifier.py
abimca-0.2.5.dist-info/LICENSE
abimca-0.2.5.dist-info/WHEEL
abimca-0.2.5.dist-info/METADATA
abimca-0.2.5.dist-info/RECORD
