Metadata-Version: 2.1
Name: abimca
Version: 0.2.5
Summary: Autoencoder based iterative modeling and multivariate time-series subsequence clustering algorithm (ABIMCA)
Home-page: https://github.com/Jokonu/abimca
License: BSD-3-Clause
Keywords: time-series,multivariate,autoencoder,subsequence,identification,clustering,algorithm
Author: Jonas Köhne
Author-email: jokohonas@gmail.com
Maintainer: Jonas Köhne
Maintainer-email: jokohonas@gmail.com
Requires-Python: >=3.9,<3.12
Classifier: Environment :: Console
Classifier: Intended Audience :: Science/Research
Classifier: License :: OSI Approved :: BSD License
Classifier: Operating System :: OS Independent
Classifier: Programming Language :: Python :: 3
Classifier: Programming Language :: Python :: 3.10
Classifier: Programming Language :: Python :: 3.9
Classifier: Topic :: Scientific/Engineering
Requires-Dist: coloredlogs (>=15.0.1,<16.0.0)
Requires-Dist: matplotlib (>=3.5.3,<4.0.0)
Requires-Dist: numpy (>=1.23.2,<2.0.0)
Requires-Dist: pandas (>=1.4.3,<2.0.0)
Requires-Dist: scikit-learn (>=1.1.2,<2.0.0)
Requires-Dist: scipy (>=1.9.0,<2.0.0)
Requires-Dist: torch (>=1.12.1,<2.0.0)
Requires-Dist: tqdm (>=4.64.0,<5.0.0)
Project-URL: Repository, https://github.com/Jokonu/abimca
